minhas_arvores/__init__.py
minhas_arvores/arvore_base.py
minhas_arvores/c45.py
minhas_arvores/cart.py
minhas_arvores/id3.py
minhas_arvores/utilidades.py
minhas_arvores-1.0.0.dist-info/licenses/LICENSE
minhas_arvores-1.0.0.dist-info/METADATA
minhas_arvores-1.0.0.dist-info/WHEEL
minhas_arvores-1.0.0.dist-info/top_level.txt
minhas_arvores-1.0.0.dist-info/RECORD
